flask_rest_jsonapi_next/__init__.py
flask_rest_jsonapi_next/api.py
flask_rest_jsonapi_next/decorators.py
flask_rest_jsonapi_next/errors.py
flask_rest_jsonapi_next/exceptions.py
flask_rest_jsonapi_next/pagination.py
flask_rest_jsonapi_next/querystring.py
flask_rest_jsonapi_next/resource.py
flask_rest_jsonapi_next/schema.py
flask_rest_jsonapi_next/data_layers/__init__.py
flask_rest_jsonapi_next/data_layers/alchemy.py
flask_rest_jsonapi_next/data_layers/base.py
flask_rest_jsonapi_next/data_layers/filtering/__init__.py
flask_rest_jsonapi_next/data_layers/filtering/alchemy.py
flask_rest_jsonapi_next/error_responses/__init__.py
flask_rest_jsonapi_next/error_responses/error_formatters.py
flask_rest_jsonapi_next/error_responses/errors_as_json_api.py
flask_rest_jsonapi_next/error_responses/exceptions.py
flask_rest_jsonapi_next/error_responses/exception_converters/__init__.py
flask_rest_jsonapi_next/error_responses/exception_converters/base.py
flask_rest_jsonapi_next/error_responses/exception_converters/flask_rest_jsonapi.py
flask_rest_jsonapi_next/error_responses/exception_converters/marshamallow.py
flask_rest_jsonapi_next/error_responses/exception_converters/sqlalchemy.py
flask_rest_jsonapi_next/error_responses/exception_converters/werkzeug.py
flask_rest_jsonapi_next-0.44.2.dist-info/licenses/LICENSE
flask_rest_jsonapi_next-0.44.2.dist-info/METADATA
flask_rest_jsonapi_next-0.44.2.dist-info/WHEEL
flask_rest_jsonapi_next-0.44.2.dist-info/top_level.txt
flask_rest_jsonapi_next-0.44.2.dist-info/RECORD
