Metadata-Version: 2.4
Name: flask-rest-jsonapi-next
Version: 0.44.2
Summary: Flask extension to create REST web api according to JSONAPI 1.0 specification with Flask, Marshmallow and data provider of your choice (SQLAlchemy, MongoDB, ...)
Author: original miLibris/flask-rest-jsonapi contributors
Maintainer-email: Tomislav Adamic <tomislav.adamic@gmail.com>
License-Expression: MIT
Project-URL: Source, https://github.com/tadams42/flask-rest-jsonapi-next
Project-URL: Documentation, https://flask-rest-jsonapi-next.readthedocs.io/en/latest/
Keywords: web,api,rest,jsonapi,flask,sqlalchemy,marshmallow
Platform: any
Classifier: Framework :: Flask
Classifier: Programming Language :: Python :: 3
Classifier: Programming Language :: Python :: 3.9
Classifier: Programming Language :: Python :: 3.10
Classifier: Programming Language :: Python :: 3.11
Classifier: Programming Language :: Python :: 3.12
Classifier: Programming Language :: Python :: 3.13
Classifier: Programming Language :: Python :: 3 :: Only
Requires-Python: >=3.9
License-File: LICENSE
Requires-Dist: Flask>=2.2.0
Requires-Dist: marshmallow<4
Requires-Dist: marshmallow-jsonapi-minfork
Requires-Dist: sqlalchemy
Requires-Dist: requests
Requires-Dist: packaging
Requires-Dist: python-dateutil
Provides-Extra: docs
Requires-Dist: furo; extra == "docs"
Requires-Dist: myst-parser; extra == "docs"
Requires-Dist: sphinx; extra == "docs"
Requires-Dist: sphinx-copybutton; extra == "docs"
Dynamic: license-file
